autopdf/__init__.py
autopdf/clusterer.py
autopdf/editor.py
autopdf/exporting.py
autopdf/to_md.py
autopdf/to_txt.py
autopdf-0.0.75.dist-info/METADATA
autopdf-0.0.75.dist-info/WHEEL
autopdf-0.0.75.dist-info/licenses/LICENSE
autopdf-0.0.75.dist-info/RECORD
